{
  "version": "2.0.8",
  "summary": {
    "title": "Surgeon App Threat Model",
    "owner": "",
    "description": "This system allows a surgeon in one city to assist a surgeon in another city with an operation, via internet connection. ",
    "id": 0
  },
  "detail": {
    "contributors": [],
    "diagrams": [
      {
        "id": 0,
        "title": "Surgeon App Threat Modeling",
        "diagramType": "STRIDE",
        "placeholder": "New STRIDE diagram description",
        "thumbnail": "./public/content/images/thumbnail.stride.jpg",
        "version": "2.0.8",
        "cells": [
          {
            "shape": "flow",
            "attrs": {
              "line": {
                "stroke": "#333333",
                "targetMarker": {
                  "name": "block"
                },
                "sourceMarker": {
                  "name": ""
                },
                "strokeDasharray": null
              }
            },
            "width": 200,
            "height": 100,
            "zIndex": 10,
            "connector": "smooth",
            "data": {
              "type": "tm.Flow",
              "name": "Data Flow",
              "description": "",
              "outOfScope": false,
              "isBidirectional": false,
              "reasonOutOfScope": "",
              "protocol": "",
              "isEncrypted": false,
              "isPublicNetwork": false,
              "hasOpenThreats": false,
              "threats": []
            },
            "id": "7a8e0ca4-1699-4d78-8095-86aeaab0857d",
            "source": {
              "x": 140,
              "y": 485
            },
            "target": {
              "cell": "88b6524e-d365-486a-a8ef-b2f9f72f5314"
            },
            "vertices": [
              {
                "x": 420,
                "y": 450
              }
            ],
            "labels": [
              "Data Flow"
            ]
          },
          {
            "shape": "flow",
            "attrs": {
              "line": {
                "stroke": "#333333",
                "targetMarker": {
                  "name": "block"
                },
                "sourceMarker": {
                  "name": ""
                },
                "strokeDasharray": null
              }
            },
            "width": 200,
            "height": 100,
            "zIndex": 10,
            "connector": "smooth",
            "data": {
              "type": "tm.Flow",
              "name": "Data Flow",
              "description": "",
              "outOfScope": false,
              "isBidirectional": false,
              "reasonOutOfScope": "",
              "protocol": "",
              "isEncrypted": false,
              "isPublicNetwork": false,
              "hasOpenThreats": false,
              "threats": []
            },
            "id": "fdcd05c5-59dc-4919-b255-4d3f9b763e39",
            "source": {
              "x": 504,
              "y": 263
            },
            "target": {
              "x": 140,
              "y": 450
            },
            "vertices": [
              {
                "x": 250,
                "y": 330
              }
            ],
            "labels": [
              "Data Flow"
            ]
          },
          {
            "shape": "flow",
            "attrs": {
              "line": {
                "stroke": "#333333",
                "targetMarker": {
                  "name": "block"
                },
                "sourceMarker": {
                  "name": ""
                },
                "strokeDasharray": null
              }
            },
            "width": 200,
            "height": 100,
            "zIndex": 10,
            "connector": "smooth",
            "data": {
              "type": "tm.Flow",
              "name": "Data Flow",
              "description": "",
              "outOfScope": false,
              "isBidirectional": false,
              "reasonOutOfScope": "",
              "protocol": "",
              "isEncrypted": false,
              "isPublicNetwork": false,
              "hasOpenThreats": false,
              "threats": []
            },
            "id": "cf81d6f1-dcf8-4cef-bbcb-eb354fe776b5",
            "source": {
              "x": 270,
              "y": 60
            },
            "target": {
              "cell": "88b6524e-d365-486a-a8ef-b2f9f72f5314"
            },
            "vertices": [
              {
                "x": 430,
                "y": 60
              },
              {
                "x": 430,
                "y": 80
              },
              {
                "x": 460,
                "y": 120
              }
            ],
            "labels": [
              "Data Flow"
            ]
          },
          {
            "shape": "flow",
            "attrs": {
              "line": {
                "stroke": "#333333",
                "targetMarker": {
                  "name": "block"
                },
                "sourceMarker": {
                  "name": ""
                },
                "strokeDasharray": null
              }
            },
            "width": 200,
            "height": 100,
            "zIndex": 10,
            "connector": "smooth",
            "data": {
              "type": "tm.Flow",
              "name": "Data Flow",
              "description": "",
              "outOfScope": false,
              "isBidirectional": false,
              "reasonOutOfScope": "",
              "protocol": "",
              "isEncrypted": false,
              "isPublicNetwork": false,
              "hasOpenThreats": false,
              "threats": []
            },
            "id": "0f23a6b8-9082-4af1-8f2e-53360f2ce428",
            "source": {
              "x": 500,
              "y": 240
            },
            "target": {
              "x": 270,
              "y": 110
            },
            "vertices": [
              {
                "x": 360,
                "y": 210
              }
            ],
            "labels": [
              "Data Flow"
            ]
          },
          {
            "shape": "flow",
            "attrs": {
              "line": {
                "stroke": "#333333",
                "targetMarker": {
                  "name": "block"
                },
                "sourceMarker": {
                  "name": ""
                },
                "strokeDasharray": null
              }
            },
            "width": 200,
            "height": 100,
            "zIndex": 10,
            "connector": "smooth",
            "data": {
              "type": "tm.Flow",
              "name": "Data Flow",
              "description": "",
              "outOfScope": false,
              "isBidirectional": false,
              "reasonOutOfScope": "",
              "protocol": "",
              "isEncrypted": false,
              "isPublicNetwork": false,
              "hasOpenThreats": false,
              "threats": []
            },
            "id": "ee2a42e0-e5f3-4cbd-a084-abfb0a936f41",
            "source": {
              "cell": "1681ffb2-1d3d-486b-ab7a-758d7c1542df"
            },
            "target": {
              "x": -50,
              "y": 110
            }
          },
          {
            "shape": "flow",
            "attrs": {
              "line": {
                "stroke": "#333333",
                "targetMarker": {
                  "name": "block"
                },
                "sourceMarker": {
                  "name": ""
                },
                "strokeDasharray": null
              }
            },
            "width": 200,
            "height": 100,
            "zIndex": 10,
            "connector": "smooth",
            "data": {
              "type": "tm.Flow",
              "name": "Data Flow",
              "description": "",
              "outOfScope": false,
              "isBidirectional": false,
              "reasonOutOfScope": "",
              "protocol": "",
              "isEncrypted": false,
              "isPublicNetwork": false,
              "hasOpenThreats": false,
              "threats": []
            },
            "id": "2bedb9db-44b4-40f0-b244-f68fa2cb1bcc",
            "source": {
              "cell": "6123b853-9587-4852-9e45-3b2ae4820fb3"
            },
            "target": {
              "x": -150,
              "y": 460
            }
          },
          {
            "shape": "flow",
            "attrs": {
              "line": {
                "stroke": "#333333",
                "targetMarker": {
                  "name": "block"
                },
                "sourceMarker": {
                  "name": ""
                },
                "strokeDasharray": null
              }
            },
            "width": 200,
            "height": 100,
            "zIndex": 10,
            "connector": "smooth",
            "data": {
              "type": "tm.Flow",
              "name": "Data Flow",
              "description": "",
              "outOfScope": false,
              "isBidirectional": false,
              "reasonOutOfScope": "",
              "protocol": "",
              "isEncrypted": false,
              "isPublicNetwork": false,
              "hasOpenThreats": false,
              "threats": []
            },
            "id": "2731da3d-251f-461f-a9bf-3d9c5a62aa7a",
            "source": {
              "x": -157,
              "y": 500
            },
            "target": {
              "cell": "6123b853-9587-4852-9e45-3b2ae4820fb3"
            },
            "vertices": [
              {
                "x": -100,
                "y": 500
              },
              {
                "x": -100,
                "y": 580
              },
              {
                "x": -30,
                "y": 580
              }
            ]
          },
          {
            "position": {
              "x": 470,
              "y": 190
            },
            "size": {
              "width": 180,
              "height": 110
            },
            "attrs": {
              "text": {
                "text": "Server"
              },
              "body": {
                "stroke": "#333333",
                "strokeWidth": 1.5,
                "strokeDasharray": null
              }
            },
            "visible": true,
            "shape": "process",
            "id": "88b6524e-d365-486a-a8ef-b2f9f72f5314",
            "zIndex": 11,
            "data": {
              "type": "tm.Process",
              "name": "Server",
              "description": "",
              "outOfScope": false,
              "reasonOutOfScope": "",
              "privilegeLevel": "",
              "hasOpenThreats": false,
              "threats": []
            }
          },
          {
            "position": {
              "x": -270,
              "y": 440
            },
            "size": {
              "width": 112.5,
              "height": 60
            },
            "attrs": {
              "text": {
                "text": "Virtual surgeon\n"
              },
              "body": {
                "stroke": "#333333",
                "strokeWidth": 1.5,
                "strokeDasharray": null
              }
            },
            "visible": true,
            "shape": "actor",
            "id": "29b11cda-e770-4a0b-affd-055d24eea60b",
            "zIndex": 14,
            "data": {
              "type": "tm.Actor",
              "name": "Virtual surgeon\n",
              "description": "",
              "outOfScope": false,
              "reasonOutOfScope": "",
              "providesAuthentication": false,
              "hasOpenThreats": false,
              "threats": []
            }
          },
          {
            "position": {
              "x": 20,
              "y": -10
            },
            "size": {
              "width": 290,
              "height": 200
            },
            "attrs": {
              "text": {
                "text": "Process translating \nsurgical commands to actions"
              },
              "body": {
                "stroke": "#333333",
                "strokeWidth": 1.5,
                "strokeDasharray": null
              }
            },
            "visible": true,
            "shape": "process",
            "id": "1681ffb2-1d3d-486b-ab7a-758d7c1542df",
            "zIndex": 15,
            "data": {
              "type": "tm.Process",
              "name": "Process translating \nsurgical commands to actions",
              "description": "",
              "outOfScope": false,
              "reasonOutOfScope": "",
              "privilegeLevel": "",
              "hasOpenThreats": false,
              "threats": []
            }
          },
          {
            "position": {
              "x": -170,
              "y": 90
            },
            "size": {
              "width": 112.5,
              "height": 60
            },
            "attrs": {
              "text": {
                "text": "Robot"
              },
              "body": {
                "stroke": "#333333",
                "strokeWidth": 1.5,
                "strokeDasharray": null
              }
            },
            "visible": true,
            "shape": "actor",
            "id": "8ff68ab2-8fb6-42ce-9ad1-105bb66c6f73",
            "zIndex": 16,
            "data": {
              "type": "tm.Actor",
              "name": "Robot",
              "description": "",
              "outOfScope": false,
              "reasonOutOfScope": "",
              "providesAuthentication": false,
              "hasOpenThreats": false,
              "threats": []
            }
          },
          {
            "position": {
              "x": -19.99999999999993,
              "y": 400
            },
            "size": {
              "width": 160,
              "height": 140
            },
            "attrs": {
              "text": {
                "text": "Surgeon UI\n"
              },
              "body": {
                "stroke": "#333333",
                "strokeWidth": 1.5,
                "strokeDasharray": null
              }
            },
            "visible": true,
            "shape": "process",
            "id": "6123b853-9587-4852-9e45-3b2ae4820fb3",
            "zIndex": 17,
            "data": {
              "type": "tm.Process",
              "name": "Surgeon UI\n",
              "description": "",
              "outOfScope": false,
              "reasonOutOfScope": "",
              "privilegeLevel": "",
              "hasOpenThreats": false,
              "threats": []
            }
          }
        ]
      }
    ],
    "diagramTop": 1,
    "reviewer": "",
    "threatTop": 0
  }
}